ShockFinder/Config.py
ShockFinder/Data.py
ShockFinder/DataBase.py
ShockFinder/Loader.py
ShockFinder/Update.py
ShockFinder/__init__.py
ShockFinder/Addon/ConfigReader.py
ShockFinder/Addon/Time.py
ShockFinder/Addon/__init__.py
ShockFinder/Addon/AnalysisTool/AnalysisToolModel.py
ShockFinder/Addon/AnalysisTool/Basic.py
ShockFinder/Addon/AnalysisTool/Bremsstrahlung.py
ShockFinder/Addon/AnalysisTool/BruntVaisalaFrequency.py
ShockFinder/Addon/AnalysisTool/Config.py
ShockFinder/Addon/AnalysisTool/Differential.py
ShockFinder/Addon/AnalysisTool/Entropy.py
ShockFinder/Addon/AnalysisTool/Equilibrium.py
ShockFinder/Addon/AnalysisTool/FastFourierTransform.py
ShockFinder/Addon/AnalysisTool/Harmonic.py
ShockFinder/Addon/AnalysisTool/KHI.py
ShockFinder/Addon/AnalysisTool/MachNumber.py
ShockFinder/Addon/AnalysisTool/MassFlux.py
ShockFinder/Addon/AnalysisTool/Mean.py
ShockFinder/Addon/AnalysisTool/RMI.py
ShockFinder/Addon/AnalysisTool/Radial.py
ShockFinder/Addon/AnalysisTool/ScalingSlope.py
ShockFinder/Addon/AnalysisTool/Shocks.py
ShockFinder/Addon/AnalysisTool/SoundSpeed.py
ShockFinder/Addon/AnalysisTool/Temperature.py
ShockFinder/Addon/AnalysisTool/TestData.py
ShockFinder/Addon/AnalysisTool/Velocity.py
ShockFinder/Addon/AnalysisTool/__init__.py
ShockFinder/Addon/GUI/Config.py
ShockFinder/Addon/GUI/XUI.py
ShockFinder/Addon/GUI/__init__.py
ShockFinder/Addon/GUI/XUIlib/Config.py
ShockFinder/Addon/GUI/XUIlib/ShockFinderFiguresHDF5.py
ShockFinder/Addon/GUI/XUIlib/SystemInfo.py
ShockFinder/Addon/GUI/XUIlib/XUIConfig.py
ShockFinder/Addon/GUI/XUIlib/__init__.py
ShockFinder/Addon/GUI/XUIlib/imgtool.py
ShockFinder/Addon/GUI/XUIlib/page.py
ShockFinder/Addon/GUI/XUIlib/progress.py
ShockFinder/Addon/GUI/XUIlib/image/Main_logo.py
ShockFinder/Addon/GUI/XUIlib/image/__init__.py
ShockFinder/Addon/GUI/XUIlib/image/config.py
ShockFinder/Addon/GUI/XUIlib/pages/Analyze.py
ShockFinder/Addon/GUI/XUIlib/pages/Exit.py
ShockFinder/Addon/GUI/XUIlib/pages/Figure.py
ShockFinder/Addon/GUI/XUIlib/pages/Help.py
ShockFinder-7.4.7.dist-info/LICENSE.txt
ShockFinder-7.4.7.dist-info/METADATA
ShockFinder-7.4.7.dist-info/WHEEL
ShockFinder-7.4.7.dist-info/top_level.txt
ShockFinder-7.4.7.dist-info/RECORD
