Metadata-Version: 2.1
Name: ShockFinder
Version: 7.4.7
Summary: ShockFinder is an interactive scientic simulation data analysis software based on python and supports multi-process, multi-mode, I/O access and drawing.
Home-page: https://github.com/wacmkxiaoyi/Shockfinder
Author: Junxiang H. & C. B. Singh
Author-email: huangjunxiang@mail.ynu.edu.cn
Classifier: Programming Language :: Python :: 3
Classifier: License :: OSI Approved :: MIT License
Classifier: Operating System :: OS Independent
Requires-Python: >=3.6
License-File: LICENSE.txt
